waylay/services/alarms/models/__init__.py
waylay/services/alarms/models/alarm_audit_record.py
waylay/services/alarms/models/alarm_entity.py
waylay/services/alarms/models/alarm_event.py
waylay/services/alarms/models/alarm_event_alarm.py
waylay/services/alarms/models/alarm_event_changes_inner.py
waylay/services/alarms/models/alarm_event_changes_inner_type.py
waylay/services/alarms/models/alarm_event_type.py
waylay/services/alarms/models/alarm_event_type_one_of.py
waylay/services/alarms/models/alarm_event_type_one_of1.py
waylay/services/alarms/models/alarm_event_type_one_of2.py
waylay/services/alarms/models/alarm_severity.py
waylay/services/alarms/models/alarm_severity_filter.py
waylay/services/alarms/models/alarm_source_filter.py
waylay/services/alarms/models/alarm_status.py
waylay/services/alarms/models/alarm_status_filter.py
waylay/services/alarms/models/alarm_timeline_info.py
waylay/services/alarms/models/alarm_type_filter.py
waylay/services/alarms/models/alarm_update.py
waylay/services/alarms/models/alarms_query_result.py
waylay/services/alarms/models/alarms_timeline_item.py
waylay/services/alarms/models/batch_alarm.py
waylay/services/alarms/models/batch_alarm_entity.py
waylay/services/alarms/models/batch_alarms_specification.py
waylay/services/alarms/models/batch_delete_alarm.py
waylay/services/alarms/models/batch_delete_alarm_all_of_action.py
waylay/services/alarms/models/batch_delete_alarm_all_of_query.py
waylay/services/alarms/models/batch_operation.py
waylay/services/alarms/models/batch_operation_enqueued.py
waylay/services/alarms/models/batch_operation_enqueued_entity.py
waylay/services/alarms/models/batch_operation_operation.py
waylay/services/alarms/models/batch_operation_operation_action.py
waylay/services/alarms/models/batch_operation_result.py
waylay/services/alarms/models/batch_operation_results.py
waylay/services/alarms/models/batch_update_alarm.py
waylay/services/alarms/models/batch_update_alarm_all_of_action.py
waylay_sdk_alarms_types-1.13.1.20241025.dist-info/LICENSE.txt
waylay_sdk_alarms_types-1.13.1.20241025.dist-info/METADATA
waylay_sdk_alarms_types-1.13.1.20241025.dist-info/WHEEL
waylay_sdk_alarms_types-1.13.1.20241025.dist-info/top_level.txt
waylay_sdk_alarms_types-1.13.1.20241025.dist-info/RECORD
